mycalc/calculator.py
mycalc_test-0.0.1.dist-info/LICENSE
mycalc_test-0.0.1.dist-info/METADATA
mycalc_test-0.0.1.dist-info/WHEEL
mycalc_test-0.0.1.dist-info/top_level.txt
mycalc_test-0.0.1.dist-info/RECORD
