Metadata-Version: 2.1
Name: mycalc-test
Version: 0.0.1
Summary: calculator test in pypi
Home-page: https://github.com/leej1212/mycalc
Download-URL: https://github.com/leej1212/mycalc/
Author: leej1212
Classifier: Programming Language :: Python :: 3
License-File: LICENSE
